<nav class="navbar navbar-expand-lg navbar-dark bg-primary mb-4">

  <div class="container">
    <a class="navbar-brand" href="https://www.dita-ot.org/">DITA Bootstrap</a>
    <button class="navbar-toggler" type="button" data-bs-toggle="collapse" data-bs-target="#navbarSupportedContent" aria-controls="navbarSupportedContent" aria-expanded="false" aria-label="Toggle navigation">
      <span class="navbar-toggler-icon"></span>
    </button>
    <div class="collapse navbar-collapse" id="navbarSupportedContent">
      <ul class="navbar-nav">
        <li class="nav-item"><a class="nav-link" href="https://www.dita-ot.org/dev">Docs</a></li>
        <li class="nav-item"><a class="nav-link" href="https://www.dita-ot.org/download">Download</a></li>
        <li class="nav-item"><a class="nav-link" href="https://www.dita-ot.org/plugins">Plugins</a></li>
        <li class="nav-item"><a class="nav-link" href="https://getbootstrap.com/docs/5.0">Bootstrap 5.0</a></li>
      </ul>
    </div>
  </div>
</nav>
